{
  "name": "Follow the Arrow",
  "board_size": 5,
  "tiles": [
    [
      2,
      3,
      "Floor",
      false
    ],
    [
      3,
      1,
      "Floor",
      false
    ],
    [
      4,
      4,
      {
        "Goal": 4
      },
      false
    ],
    [
      2,
      1,
      "Floor",
      false
    ],
    [
      1,
      0,
      "Floor",
      false
    ],
    [
      4,
      2,
      {
        "TurnBut": [
          7,
          "South"
        ]
      },
      true
    ],
    [
      0,
      1,
      {
        "Goal": 8
      },
      false
    ],
    [
      2,
      2,
      "Floor",
      false
    ],
    [
      3,
      3,
      "Floor",
      false
    ],
    [
      3,
      2,
      "Floor",
      false
    ],
    [
      2,
      0,
      "Floor",
      false
    ],
    [
      3,
      0,
      "Floor",
      false
    ],
    [
      0,
      4,
      "Floor",
      false
    ],
    [
      0,
      3,
      "Floor",
      false
    ],
    [
      4,
      0,
      {
        "Source": [
          8,
          "South"
        ]
      },
      false
    ],
    [
      1,
      1,
      "Floor",
      false
    ],
    [
      2,
      4,
      "Floor",
      false
    ],
    [
      0,
      2,
      "Floor",
      false
    ],
    [
      3,
      4,
      "Floor",
      false
    ],
    [
      1,
      4,
      "Floor",
      false
    ],
    [
      4,
      3,
      "Floor",
      false
    ],
    [
      1,
      3,
      "Floor",
      false
    ],
    [
      0,
      0,
      "Floor",
      false
    ],
    [
      4,
      1,
      {
        "Arrow": [
          8,
          "West"
        ]
      },
      true
    ],
    [
      1,
      2,
      {
        "Source": [
          4,
          "East"
        ]
      },
      false
    ]
  ],
  "solution": [
    [
      4,
      2,
      {
        "TurnBut": [
          7,
          "South"
        ]
      }
    ],
    [
      4,
      1,
      {
        "Arrow": [
          8,
          "West"
        ]
      }
    ]
  ],
  "seed": 8222229090223304252,
  "difficulty": 46
}